llmsbrieftxt/__init__.py
llmsbrieftxt/cli.py
llmsbrieftxt/constants.py
llmsbrieftxt/crawler.py
llmsbrieftxt/doc_loader.py
llmsbrieftxt/extractor.py
llmsbrieftxt/main.py
llmsbrieftxt/schema.py
llmsbrieftxt/summarizer.py
llmsbrieftxt/url_filters.py
llmsbrieftxt/url_utils.py
llmsbrieftxt-1.11.1.dist-info/METADATA
llmsbrieftxt-1.11.1.dist-info/WHEEL
llmsbrieftxt-1.11.1.dist-info/entry_points.txt
llmsbrieftxt-1.11.1.dist-info/licenses/LICENSE
llmsbrieftxt-1.11.1.dist-info/RECORD
