Metadata-Version: 2.4
Name: llmsbrieftxt
Version: 1.11.1
Summary: Generate llms-brief.txt files from documentation websites using AI
Project-URL: Homepage, https://github.com/stevennevins/llmsbrief
Project-URL: Repository, https://github.com/stevennevins/llmsbrief
Project-URL: Issues, https://github.com/stevennevins/llmsbrief/issues
Project-URL: Documentation, https://github.com/stevennevins/llmsbrief#readme
Author: llmsbrieftxt contributors
License: MIT
License-File: LICENSE
Keywords: ai,crawling,documentation,llm,llms-brief,llmstxt,openai,summarization,web-scraping
Classifier: Development Status :: 4 - Beta
Classifier: Intended Audience :: Developers
Classifier: License :: OSI Approved :: MIT License
Classifier: Programming Language :: Python :: 3
Classifier: Programming Language :: Python :: 3.10
Classifier: Programming Language :: Python :: 3.11
Classifier: Programming Language :: Python :: 3.12
Classifier: Topic :: Internet :: WWW/HTTP :: Indexing/Search
Classifier: Topic :: Software Development :: Documentation
Classifier: Topic :: Text Processing :: Markup :: Markdown
Requires-Python: >=3.10
Requires-Dist: beautifulsoup4>=4.13.5
Requires-Dist: httpx<1.0.0,>=0.28.1
Requires-Dist: openai<2.0.0,>=1.54.0
Requires-Dist: pydantic<3.0.0,>=2.10.1
Requires-Dist: tenacity<10.0.0,>=9.1.2
Requires-Dist: tqdm<5.0.0,>=4.66.0
Requires-Dist: trafilatura>=2.0.0
Requires-Dist: ultimate-sitemap-parser>=1.6.0
